my_userparam/__init__.py
my_userparam/main.py
my_userparam/typers/__init__.py
my_userparam/typers/alias.py
my_userparam/typers/ssh.py
my_userparam/typers/ssh_keys.py
my_userparam/typers/totp.py
my_userparam-0.1.dist-info/licenses/LICENSE
my_userparam-0.1.dist-info/METADATA
my_userparam-0.1.dist-info/WHEEL
my_userparam-0.1.dist-info/entry_points.txt
my_userparam-0.1.dist-info/top_level.txt
my_userparam-0.1.dist-info/RECORD
