Metadata-Version: 2.4
Name: my_userparam
Version: 0.1
Summary: Tools to quickly get all my env variables and config.
Author-email: Arnaud Kientz <arnaud@linuxmuster.net>
License-Expression: GPL-3.0
Project-URL: Homepage, https://github.com/kiarn/my
Project-URL: Issues, https://github.com/kiarn/my/issues
Classifier: Programming Language :: Python :: 3
Classifier: Operating System :: POSIX :: Linux
Requires-Python: >=3.8
License-File: LICENSE
Requires-Dist: cryptography
Requires-Dist: pyotp
Requires-Dist: ssh_config
Requires-Dist: termcolor
Requires-Dist: typer
Dynamic: license-file
